camera_calibration/__init__.py
camera_calibration/analyze.py
camera_calibration/colmap.py
camera_calibration/visualize.py
wf_camera_calibration-0.5.0.dist-info/LICENSE
wf_camera_calibration-0.5.0.dist-info/METADATA
wf_camera_calibration-0.5.0.dist-info/WHEEL
wf_camera_calibration-0.5.0.dist-info/top_level.txt
wf_camera_calibration-0.5.0.dist-info/RECORD
