Metadata-Version: 2.1
Name: wf-camera-calibration
Version: 0.5.0
Summary: Support for calculating intrinsic and extrinsic camera calibration parameters using COLMAP and other tools
Home-page: https://github.com/WildflowerSchools/wf-camera-calibration
Author: Theodore Quinn
Author-email: ted.quinn@wildflowerschools.org
License: UNKNOWN
Platform: UNKNOWN
Classifier: Intended Audience :: Developers
Classifier: License :: OSI Approved :: MIT License
Classifier: Operating System :: OS Independent
Classifier: Programming Language :: Python
License-File: LICENSE
Requires-Dist: wf-cv-utils (>=3.0.0)
Requires-Dist: wf-honeycomb-io (>=0.3.0)
Requires-Dist: wf-video-io (>=1.0.0)
Requires-Dist: pandas (>=1.2.2)
Requires-Dist: numpy (>=1.20.1)
Requires-Dist: opencv-python (>=4.5.1)
